sciolyid/__init__.py
sciolyid/__main__.py
sciolyid/config.py
sciolyid/core.py
sciolyid/data.py
sciolyid/data_functions.py
sciolyid/downloads.py
sciolyid/functions.py
sciolyid/start_bot.py
sciolyid/util.py
sciolyid/cogs/__init__.py
sciolyid/cogs/check.py
sciolyid/cogs/hint.py
sciolyid/cogs/media.py
sciolyid/cogs/meta.py
sciolyid/cogs/other.py
sciolyid/cogs/race.py
sciolyid/cogs/score.py
sciolyid/cogs/sessions.py
sciolyid/cogs/skip.py
sciolyid/cogs/state.py
sciolyid/cogs/stats.py
sciolyid/scripts/__init__.py
sciolyid/scripts/find_duplicates.py
sciolyid/scripts/generate_file_structure.py
sciolyid/scripts/generate_wiki.py
sciolyid/scripts/install_redis.py
sciolyid/scripts/restore_backup.py
sciolyid/web/__init__.py
sciolyid/web/config.py
sciolyid/web/git.py
sciolyid/web/main.py
sciolyid/web/blueprints/__init__.py
sciolyid/web/blueprints/about.py
sciolyid/web/blueprints/upload.py
sciolyid/web/blueprints/user.py
sciolyid/web/blueprints/verify.py
sciolyid/web/functions/__init__.py
sciolyid/web/functions/images.py
sciolyid/web/functions/user.py
sciolyid/web/functions/webhooks.py
sciolyid/web/tasks/__init__.py
sciolyid/web/tasks/git_tasks.py
sciolyid-2.0.2.dist-info/LICENSE
sciolyid-2.0.2.dist-info/METADATA
sciolyid-2.0.2.dist-info/WHEEL
sciolyid-2.0.2.dist-info/top_level.txt
sciolyid-2.0.2.dist-info/RECORD
