Metadata-Version: 2.1
Name: sciolyid
Version: 2.0.2
Summary: Create ID Discord bots for SciOly studying.
Home-page: https://github.com/tctree333/SciOly-ID
Author: Tomi Chen
Author-email: pypi@tomichen.com
License: GPLv3+
Keywords: science_olympiad discord_bot discord studying
Classifier: Development Status :: 4 - Beta
Classifier: License :: OSI Approved :: GNU General Public License v3 or later (GPLv3+)
Classifier: Programming Language :: Python :: 3.8
Classifier: Programming Language :: Python :: 3.9
Classifier: Programming Language :: Python :: 3.10
Classifier: Programming Language :: Python :: 3.11
Requires-Python: >=3.8
License-File: LICENSE
Requires-Dist: discord.py (<3.0.0,>=2.3.1)
Requires-Dist: redis (<5.0.0,>=3.3.5)
Requires-Dist: sentry-sdk (<2.0.0,>=1.1.0)
Requires-Dist: Pillow (<11.0.0,>=9.0.1)
Requires-Dist: wikipedia (<2.0.0,>=1.4.0)
Requires-Dist: gitpython (<4.0.0,>=3.0.6)
Requires-Dist: hiredis (<3.0.0,>=1.0.1)
Requires-Dist: pandas (<3.0.0,>=1.3.0)
Requires-Dist: filelock (<3.7.0,>=3.4.2)
Provides-Extra: web
Requires-Dist: Flask (<2.1.0,>=1.1.2) ; extra == 'web'
Requires-Dist: Authlib (<1.0.0,>=0.15.5) ; extra == 'web'
Requires-Dist: gunicorn (<21.0.0,>=20.0.4) ; extra == 'web'
Requires-Dist: ImageHash (<5.0.0,>=4.0.0) ; extra == 'web'
Requires-Dist: Celery (<5.0.0,>=4.4.3) ; extra == 'web'
Requires-Dist: blinker (<1.5,>=1.4) ; extra == 'web'
